[
  {
    "state-province": null,
    "name": "Barcelona Graduate School of Economics",
    "web_pages": [
      "http://www.barcelonagse.eu/"
    ],
    "country": "Spain",
    "domains": [
      "barcelonagse.eu"
    ],
    "alpha_two_code": "ES"
  },
  {
    "state-province": null,
    "name": "Bircham International University",
    "web_pages": [
      "http://www.bircham.edu/"
    ],
    "country": "Spain",
    "domains": [
      "bircham.edu"
    ],
    "alpha_two_code": "ES"
  },
  {
    "state-province": null,
    "name": "Universidad de San Pablo CEU",
    "web_pages": [
      "http://www.ceu.es/"
    ],
    "country": "Spain",
    "domains": [
      "ceu.es"
    ],
    "alpha_two_code": "ES"
  },
  {
    "state-province": null,
    "name": "Universidad de Deusto",
    "web_pages": [
      "http://www.deusto.es/"
    ],
    "country": "Spain",
    "domains": [
      "deusto.es"
    ],
    "alpha_two_code": "ES"
  },
  {
    "state-province": null,
    "name": "Universidad del Pa\u00eds Vasco",
    "web_pages": [
      "http://www.ehu.es/"
    ],
    "country": "Spain",
    "domains": [
      "ehu.es",
      "ehu.eus"
    ],
    "alpha_two_code": "ES"
  },
  {
    "state-province": null,
    "name": "Escuela Superior de Gestion Comercial y Marketing (ESIC)",
    "web_pages": [
      "http://www.esic.es/"
    ],
    "country": "Spain",
    "domains": [
      "esic.es"
    ],
    "alpha_two_code": "ES"
  },
  {
    "state-province": null,
    "name": "Global Business School Barcelona",
    "web_pages": [
      "http://www.global-business-school.org/"
    ],
    "country": "Spain",
    "domains": [
      "global-business-school.org"
    ],
    "alpha_two_code": "ES"
  },
  {
    "state-province": null,
    "name": "IE University",
    "web_pages": [
      "http://www.ie.edu/"
    ],
    "country": "Spain",
    "domains": [
      "ie.edu"
    ],
    "alpha_two_code": "ES"
  },
  {
    "state-province": null,
    "name": "International University of Southern Europe",
    "web_pages": [
      "http://www.iuse.edu.es/"
    ],
    "country": "Spain",
    "domains": [
      "iuse.edu.es"
    ],
    "alpha_two_code": "ES"
  },
  {
    "state-province": null,
    "name": "La Salle Universities - International Programmes",
    "web_pages": [
      "http://www.lasalleuniversities.net/"
    ],
    "country": "Spain",
    "domains": [
      "lasalleuniversities.net"
    ],
    "alpha_two_code": "ES"
  },
  {
    "state-province": null,
    "name": "Mondragon Univertsitatea",
    "web_pages": [
      "http://www.muni.es/"
    ],
    "country": "Spain",
    "domains": [
      "muni.es",
      "mundragon.edu"
    ],
    "alpha_two_code": "ES"
  },
  {
    "state-province": null,
    "name": "La Salle - Universitat R\u00e1mon Llull",
    "web_pages": [
      "http://www.salleurl.edu/"
    ],
    "country": "Spain",
    "domains": [
      "salleurl.edu"
    ],
    "alpha_two_code": "ES"
  },
  {
    "state-province": null,
    "name": "Schiller International University, Madrid",
    "web_pages": [
      "http://www.schillermadrid.edu/"
    ],
    "country": "Spain",
    "domains": [
      "schillermadrid.edu"
    ],
    "alpha_two_code": "ES"
  },
  {
    "state-province": null,
    "name": "Universitat Aut\u00f3noma de Barcelona",
    "web_pages": [
      "http://www.uab.es/"
    ],
    "country": "Spain",
    "domains": [
      "uab.es"
    ],
    "alpha_two_code": "ES"
  },
  {
    "state-province": null,
    "name": "Universidad de Alicante",
    "web_pages": [
      "http://www.ua.es/"
    ],
    "country": "Spain",
    "domains": [
      "ua.es"
    ],
    "alpha_two_code": "ES"
  },
  {
    "state-province": null,
    "name": "Universidad de Alcal\u00e1 de Henares",
    "web_pages": [
      "http://www.uah.es/"
    ],
    "country": "Spain",
    "domains": [
      "uah.es"
    ],
    "alpha_two_code": "ES"
  },
  {
    "state-province": null,
    "name": "Universidad de Almer\u00eda",
    "web_pages": [
      "http://www.ualm.es/"
    ],
    "country": "Spain",
    "domains": [
      "ualm.es"
    ],
    "alpha_two_code": "ES"
  },
  {
    "state-province": null,
    "name": "Universidad Aut\u00f3noma de Madrid",
    "web_pages": [
      "http://www.uam.es/"
    ],
    "country": "Spain",
    "domains": [
      "uam.es"
    ],
    "alpha_two_code": "ES"
  },
  {
    "state-province": null,
    "name": "Universidad Alfonso X El Sabio",
    "web_pages": [
      "http://www.uax.es/"
    ],
    "country": "Spain",
    "domains": [
      "uax.es"
    ],
    "alpha_two_code": "ES"
  },
  {
    "state-province": null,
    "name": "Universitat de Barcelona",
    "web_pages": [
      "http://www.ub.es/"
    ],
    "country": "Spain",
    "domains": [
      "ub.es"
    ],
    "alpha_two_code": "ES"
  },
  {
    "state-province": null,
    "name": "Universidad de Burgos",
    "web_pages": [
      "http://www.ubu.es/"
    ],
    "country": "Spain",
    "domains": [
      "ubu.es"
    ],
    "alpha_two_code": "ES"
  },
  {
    "state-province": null,
    "name": "Universidad Carlos III de Madrid",
    "web_pages": [
      "http://www.uc3m.es/"
    ],
    "country": "Spain",
    "domains": [
      "uc3m.es"
    ],
    "alpha_two_code": "ES"
  },
  {
    "state-province": null,
    "name": "Universidad de C\u00e1diz",
    "web_pages": [
      "http://www.uca.es/"
    ],
    "country": "Spain",
    "domains": [
      "uca.es"
    ],
    "alpha_two_code": "ES"
  },
  {
    "state-province": null,
    "name": "Universidad Cat\u00f3lica San Antonio",
    "web_pages": [
      "http://www.ucam.edu/"
    ],
    "country": "Spain",
    "domains": [
      "ucam.edu"
    ],
    "alpha_two_code": "ES"
  },
  {
    "state-province": null,
    "name": "Universidad Cat\u00f3lica de \u00c1vila",
    "web_pages": [
      "http://www.ucavila.es/"
    ],
    "country": "Spain",
    "domains": [
      "ucavila.es"
    ],
    "alpha_two_code": "ES"
  },
  {
    "state-province": null,
    "name": "Universidad Cardenal Herrera-CEU",
    "web_pages": [
      "http://www.uchceu.es/"
    ],
    "country": "Spain",
    "domains": [
      "uchceu.es"
    ],
    "alpha_two_code": "ES"
  },
  {
    "state-province": null,
    "name": "Universidad de Castilla La Mancha",
    "web_pages": [
      "http://www.uclm.es/"
    ],
    "country": "Spain",
    "domains": [
      "uclm.es"
    ],
    "alpha_two_code": "ES"
  },
  {
    "state-province": null,
    "name": "Universidad Complutense de Madrid",
    "web_pages": [
      "http://www.ucm.es/"
    ],
    "country": "Spain",
    "domains": [
      "ucm.es"
    ],
    "alpha_two_code": "ES"
  },
  {
    "state-province": null,
    "name": "Universidad de C\u00f3rdoba",
    "web_pages": [
      "http://www.uco.es/"
    ],
    "country": "Spain",
    "domains": [
      "uco.es"
    ],
    "alpha_two_code": "ES"
  },
  {
    "state-province": null,
    "name": "Universidad Cat\u00f3lica de Valencia",
    "web_pages": [
      "http://www.ucv.es/"
    ],
    "country": "Spain",
    "domains": [
      "ucv.es"
    ],
    "alpha_two_code": "ES"
  },
  {
    "state-province": null,
    "name": "Universidad de La Coru\u00f1a",
    "web_pages": [
      "http://www.udc.es/"
    ],
    "country": "Spain",
    "domains": [
      "udc.es"
    ],
    "alpha_two_code": "ES"
  },
  {
    "state-province": null,
    "name": "Universidad de Gerona",
    "web_pages": [
      "http://www.udg.es/"
    ],
    "country": "Spain",
    "domains": [
      "udg.es"
    ],
    "alpha_two_code": "ES"
  },
  {
    "state-province": null,
    "name": "Universitat de Lleida",
    "web_pages": [
      "http://www.udl.es/"
    ],
    "country": "Spain",
    "domains": [
      "udl.es"
    ],
    "alpha_two_code": "ES"
  },
  {
    "state-province": null,
    "name": "Universidad Europea de Madrid",
    "web_pages": [
      "http://www.uem.es/"
    ],
    "country": "Spain",
    "domains": [
      "uem.es"
    ],
    "alpha_two_code": "ES"
  },
  {
    "state-province": null,
    "name": "Universidad Francisco de Vitoria",
    "web_pages": [
      "http://www.ufv.es/"
    ],
    "country": "Spain",
    "domains": [
      "ufv.es"
    ],
    "alpha_two_code": "ES"
  },
  {
    "state-province": null,
    "name": "Universidad de Granada",
    "web_pages": [
      "http://www.ugr.es/"
    ],
    "country": "Spain",
    "domains": [
      "ugr.es"
    ],
    "alpha_two_code": "ES"
  },
  {
    "state-province": null,
    "name": "Universidad de Huelva",
    "web_pages": [
      "http://www.uhu.es/"
    ],
    "country": "Spain",
    "domains": [
      "uhu.es"
    ],
    "alpha_two_code": "ES"
  },
  {
    "state-province": null,
    "name": "Universidad Internacional de Andaluc\u00eda",
    "web_pages": [
      "http://www.uia.es/"
    ],
    "country": "Spain",
    "domains": [
      "uia.es"
    ],
    "alpha_two_code": "ES"
  },
  {
    "state-province": null,
    "name": "Universitat de les Illes Balears",
    "web_pages": [
      "http://www.uib.es/"
    ],
    "country": "Spain",
    "domains": [
      "uib.es"
    ],
    "alpha_two_code": "ES"
  },
  {
    "state-province": null,
    "name": "Universitat Internacional de Catalunya",
    "web_pages": [
      "http://www.uic.es/"
    ],
    "country": "Spain",
    "domains": [
      "uic.es"
    ],
    "alpha_two_code": "ES"
  },
  {
    "state-province": null,
    "name": "Universidad Internacional Men\u00e9ndez Pelayo",
    "web_pages": [
      "http://www.uimp.es/"
    ],
    "country": "Spain",
    "domains": [
      "uimp.es"
    ],
    "alpha_two_code": "ES"
  },
  {
    "state-province": null,
    "name": "Universidad de Ja\u00e9n",
    "web_pages": [
      "http://www.ujaen.es/"
    ],
    "country": "Spain",
    "domains": [
      "ujaen.es"
    ],
    "alpha_two_code": "ES"
  },
  {
    "state-province": null,
    "name": "Universitat Jaume I de Castell\u00f3n",
    "web_pages": [
      "http://www.uji.es/"
    ],
    "country": "Spain",
    "domains": [
      "uji.es"
    ],
    "alpha_two_code": "ES"
  },
  {
    "state-province": null,
    "name": "Universidad de La Laguna",
    "web_pages": [
      "http://www.ull.es/"
    ],
    "country": "Spain",
    "domains": [
      "ull.es"
    ],
    "alpha_two_code": "ES"
  },
  {
    "state-province": null,
    "name": "Universidad de Las Palmas de Gran Canaria",
    "web_pages": [
      "http://www.ulpgc.es/"
    ],
    "country": "Spain",
    "domains": [
      "ulpgc.es"
    ],
    "alpha_two_code": "ES"
  },
  {
    "state-province": null,
    "name": "Universidad de M\u00e1laga",
    "web_pages": [
      "http://www.uma.es/"
    ],
    "country": "Spain",
    "domains": [
      "uma.es"
    ],
    "alpha_two_code": "ES"
  },
  {
    "state-province": null,
    "name": "Universidad de Murcia",
    "web_pages": [
      "http://www.um.es/"
    ],
    "country": "Spain",
    "domains": [
      "um.es"
    ],
    "alpha_two_code": "ES"
  },
  {
    "state-province": null,
    "name": "Universidad Miguel Hern\u00e1ndez de Elche",
    "web_pages": [
      "http://www.umh.es/"
    ],
    "country": "Spain",
    "domains": [
      "umh.es"
    ],
    "alpha_two_code": "ES"
  },
  {
    "state-province": null,
    "name": "Universidad P\u00fablica de Navarra",
    "web_pages": [
      "http://www.unavarra.es/"
    ],
    "country": "Spain",
    "domains": [
      "unavarra.es"
    ],
    "alpha_two_code": "ES"
  },
  {
    "state-province": null,
    "name": "Universidad de Navarra",
    "web_pages": [
      "http://www.unav.es/"
    ],
    "country": "Spain",
    "domains": [
      "unav.es"
    ],
    "alpha_two_code": "ES"
  },
  {
    "state-province": null,
    "name": "Universidad Nacional de Educaci\u00f3n a Distancia",
    "web_pages": [
      "http://www.uned.es/"
    ],
    "country": "Spain",
    "domains": [
      "uned.es"
    ],
    "alpha_two_code": "ES"
  },
  {
    "state-province": null,
    "name": "Universidad de Extremadura",
    "web_pages": [
      "http://www.unex.es/"
    ],
    "country": "Spain",
    "domains": [
      "unex.es"
    ],
    "alpha_two_code": "ES"
  },
  {
    "state-province": null,
    "name": "Universidad Internacional de Andaluc\u00eda, Sede Antonio Machado de Baeza",
    "web_pages": [
      "http://www.uniaam.uia.es/"
    ],
    "country": "Spain",
    "domains": [
      "uniaam.uia.es"
    ],
    "alpha_two_code": "ES"
  },
  {
    "state-province": null,
    "name": "Universidad Loyola Andaluc\u00eda",
    "web_pages": [
      "https://www.uloyola.es/"
    ],
    "country": "Spain",
    "domains": [
      "uloyola.es"
    ],
    "alpha_two_code": "ES"
  },
  {
    "state-province": null,
    "name": "Universidad Abierta Interactiva",
    "web_pages": [
      "http://www.uniactiva.com/"
    ],
    "country": "Spain",
    "domains": [
      "uniactiva.com"
    ],
    "alpha_two_code": "ES"
  },
  {
    "state-province": null,
    "name": "Universidad Internacional de Andaluc\u00eda, Sede La R\u00e1bida",
    "web_pages": [
      "http://www.uniara.uia.es/"
    ],
    "country": "Spain",
    "domains": [
      "uniara.uia.es"
    ],
    "alpha_two_code": "ES"
  },
  {
    "state-province": null,
    "name": "Universidad de Cantabria",
    "web_pages": [
      "http://www.unican.es/"
    ],
    "country": "Spain",
    "domains": [
      "unican.es"
    ],
    "alpha_two_code": "ES"
  },
  {
    "state-province": null,
    "name": "Universidad de Le\u00f3n",
    "web_pages": [
      "http://www.unileon.es/"
    ],
    "country": "Spain",
    "domains": [
      "unileon.es"
    ],
    "alpha_two_code": "ES"
  },
  {
    "state-province": null,
    "name": "Universidad de Oviedo",
    "web_pages": [
      "http://www.uniovi.es/"
    ],
    "country": "Spain",
    "domains": [
      "uniovi.es"
    ],
    "alpha_two_code": "ES"
  },
  {
    "state-province": null,
    "name": "Universidad de La Rioja",
    "web_pages": [
      "http://www.unirioja.es/"
    ],
    "country": "Spain",
    "domains": [
      "unirioja.es"
    ],
    "alpha_two_code": "ES"
  },
  {
    "state-province": null,
    "name": "Iniciativa Universidad del Atlantico",
    "web_pages": [
      "http://www.universidadatlantico.org/"
    ],
    "country": "Spain",
    "domains": [
      "universidadatlantico.org"
    ],
    "alpha_two_code": "ES"
  },
  {
    "state-province": null,
    "name": "Universidad de Zaragoza",
    "web_pages": [
      "http://www.unizar.es/"
    ],
    "country": "Spain",
    "domains": [
      "unizar.es"
    ],
    "alpha_two_code": "ES"
  },
  {
    "state-province": null,
    "name": "Universidad Antonio de Nebrija",
    "web_pages": [
      "http://www.unnet.es/"
    ],
    "country": "Spain",
    "domains": [
      "unnet.es"
    ],
    "alpha_two_code": "ES"
  },
  {
    "state-province": null,
    "name": "Universitat Oberta de Catalunya",
    "web_pages": [
      "http://www.uoc.edu/"
    ],
    "country": "Spain",
    "domains": [
      "uoc.es",
      "uoc.edu"
    ],
    "alpha_two_code": "ES"
  },
  {
    "state-province": null,
    "name": "Universidad Polit\u00e9cnica de Cataluna",
    "web_pages": [
      "http://www.upc.edu/"
    ],
    "country": "Spain",
    "domains": [
      "upc.edu"
    ],
    "alpha_two_code": "ES"
  },
  {
    "state-province": null,
    "name": "Universidad Pontificia Comillas",
    "web_pages": [
      "http://www.upco.es/"
    ],
    "country": "Spain",
    "domains": [
      "upco.es"
    ],
    "alpha_two_code": "ES"
  },
  {
    "state-province": null,
    "name": "Universidad Polit\u00e9cnica de Cartagena",
    "web_pages": [
      "http://www.upct.es/"
    ],
    "country": "Spain",
    "domains": [
      "upct.es"
    ],
    "alpha_two_code": "ES"
  },
  {
    "state-province": null,
    "name": "Universitat Pompeu Fabra",
    "web_pages": [
      "http://www.upf.es/",
      "https://www.upf.edu/"
    ],
    "country": "Spain",
    "domains": [
      "upf.es",
      "upf.edu"
    ],
    "alpha_two_code": "ES"
  },
  {
    "state-province": null,
    "name": "Universidad Polit\u00e9cnica de Madrid",
    "web_pages": [
      "http://www.upm.es/"
    ],
    "country": "Spain",
    "domains": [
      "upm.es"
    ],
    "alpha_two_code": "ES"
  },
  {
    "state-province": null,
    "name": "Universidad Pablo de Olavide",
    "web_pages": [
      "http://www.upo.es/"
    ],
    "country": "Spain",
    "domains": [
      "upo.es"
    ],
    "alpha_two_code": "ES"
  },
  {
    "state-province": null,
    "name": "Universidad Pontificia de Salamanca",
    "web_pages": [
      "http://www.upsa.es/"
    ],
    "country": "Spain",
    "domains": [
      "upsa.es"
    ],
    "alpha_two_code": "ES"
  },
  {
    "state-province": null,
    "name": "Universidad Polit\u00e9cnica de Valencia",
    "web_pages": [
      "http://www.upv.es/"
    ],
    "country": "Spain",
    "domains": [
      "upv.es"
    ],
    "alpha_two_code": "ES"
  },
  {
    "state-province": null,
    "name": "Universidad Rey Juan Carlos",
    "web_pages": [
      "http://www.urjc.es/"
    ],
    "country": "Spain",
    "domains": [
      "urjc.es",
      "gsyc.es"
    ],
    "alpha_two_code": "ES"
  },
  {
    "state-province": null,
    "name": "Universitat R\u00e1mon Llull",
    "web_pages": [
      "http://www.url.es/"
    ],
    "country": "Spain",
    "domains": [
      "url.es"
    ],
    "alpha_two_code": "ES"
  },
  {
    "state-province": null,
    "name": "Universitat Rovira I Virgili Tarragona",
    "web_pages": [
      "http://www.urv.es/"
    ],
    "country": "Spain",
    "domains": [
      "urv.es"
    ],
    "alpha_two_code": "ES"
  },
  {
    "state-province": null,
    "name": "Universidad de Salamanca",
    "web_pages": [
      "http://www.usal.es/"
    ],
    "country": "Spain",
    "domains": [
      "usal.es"
    ],
    "alpha_two_code": "ES"
  },
  {
    "state-province": null,
    "name": "Universidad de Santiago de Compostela",
    "web_pages": [
      "http://www.usc.es/"
    ],
    "country": "Spain",
    "domains": [
      "usc.es"
    ],
    "alpha_two_code": "ES"
  },
  {
    "state-province": null,
    "name": "Universidad de Sevilla",
    "web_pages": [
      "http://www.us.es/"
    ],
    "country": "Spain",
    "domains": [
      "us.es"
    ],
    "alpha_two_code": "ES"
  },
  {
    "state-province": null,
    "name": "Universidad de Valladolid",
    "web_pages": [
      "http://www.uva.es/"
    ],
    "country": "Spain",
    "domains": [
      "uva.es"
    ],
    "alpha_two_code": "ES"
  },
  {
    "state-province": null,
    "name": "Universidad de Valencia",
    "web_pages": [
      "http://www.uv.es/"
    ],
    "country": "Spain",
    "domains": [
      "uv.es"
    ],
    "alpha_two_code": "ES"
  },
  {
    "state-province": null,
    "name": "Universitat de Vic",
    "web_pages": [
      "http://www.uvic.es/"
    ],
    "country": "Spain",
    "domains": [
      "uvic.es"
    ],
    "alpha_two_code": "ES"
  },
  {
    "state-province": null,
    "name": "Universidad de Vigo",
    "web_pages": [
      "http://www.uvigo.es/"
    ],
    "country": "Spain",
    "domains": [
      "uvigo.es"
    ],
    "alpha_two_code": "ES"
  },
  {
    "state-province": null,
    "name": "Centro Universitario Villanueva",
    "web_pages": [
      "http://www.villanueva.edu/"
    ],
    "country": "Spain",
    "domains": [
      "villanueva.edu"
    ],
    "alpha_two_code": "ES"
  },
  {
    "state-province": "Castilla la mancha",
    "name": "Universidad Internacional Isabel I",
    "web_pages": [
      "https://www.ui1.es/"
    ],
    "country": "Spain",
    "domains": [
      "ui1.es",
      "alumnos.ui1.es"
    ],
    "alpha_two_code": "ES"
  },
  {
    "state-province": null,
    "name": "ENAE Business School",
    "web_pages": [
      "https://www.enae.es/"
    ],
    "country": "Spain",
    "domains": [
      "enae.es"
    ],
    "alpha_two_code": "ES"
  },
  {
    "state-province": null,
    "name": "Universidad Internacional de Valencia",
    "web_pages": [
      "https://viu.es/"
    ],
    "country": "Spain",
    "domains": [
      "viu.es"
    ],
    "alpha_two_code": "ES"
  },
  {
    "state-province": null,
    "name": "ESADE Business & Law School",
    "web_pages": [
      "https://www.esade.edu/en/about-us/law-school"
    ],
    "country": "Spain",
    "domains": [
      "esade.edu"
    ],
    "alpha_two_code": "ES"
  },
  {
    "state-province": null,
    "name": "IESE Business School",
    "web_pages": [
      "https://www.iese.edu/"
    ],
    "country": "Spain",
    "domains": [
      "iese.edu"
    ],
    "alpha_two_code": "ES"
  },
  {
    "state-province": null,
    "name": "Eada Business School Barcelona",
    "web_pages": [
      "https://www.eada.edu/"
    ],
    "country": "Spain",
    "domains": [
      "eada.edu"
    ],
    "alpha_two_code": "ES"
  },
  {
    "state-province": null,
    "name": "University of Barcelona",
    "web_pages": [
      "https://web.ub.edu"
    ],
    "country": "Spain",
    "domains": [
      "alumnes.ub.edu"
    ],
    "alpha_two_code": "ES"
  },
  {
    "state-province": null,
    "name": "University of Girona",
    "web_pages": [
      "https://udg.edu"
    ],
    "country": "Spain",
    "domains": [
      "campus.udg.edu"
    ],
    "alpha_two_code": "ES"
  }
]